libpackages/__init__.py
libpackages/helloWorld.py
hellopackageabc-0.0.1.dist-info/METADATA
hellopackageabc-0.0.1.dist-info/WHEEL
hellopackageabc-0.0.1.dist-info/top_level.txt
hellopackageabc-0.0.1.dist-info/RECORD
